PyLMD/LMD.py
PyLMD/__init__.py
PyLMD-1.0.4.dist-info/LICENSE
PyLMD-1.0.4.dist-info/METADATA
PyLMD-1.0.4.dist-info/WHEEL
PyLMD-1.0.4.dist-info/top_level.txt
PyLMD-1.0.4.dist-info/RECORD
