Metadata-Version: 2.1
Name: PyLMD
Version: 1.0.4
Summary: Jonathan S. Smith. The local mean decomposition and its application to EEG perception data. Journal of the Royal Society Interface, 2005, 2(5): 443-454
Home-page: https://github.com/shownlin/PyLMD
Author: Lin, Qun-Wei
Author-email: r07922164@csie.ntu.edu.tw
License: UNKNOWN
Platform: UNKNOWN
Classifier: Programming Language :: Python :: 3
Classifier: License :: OSI Approved :: MIT License
Classifier: Operating System :: OS Independent
Requires-Python: >=3.6
